{"activities":[],"goals":{"activeMinutes":30,"caloriesOut":2605,"distance":8.05,"floors":10,"steps":10000},"summary":{"activeScore":-1,"activityCalories":1327,"caloriesBMR":1672,"caloriesOut":2742,"distances":[{"activity":"total","distance":7.34},{"activity":"tracker","distance":7.34},{"activity":"loggedActivities","distance":0},{"activity":"veryActive","distance":3.19},{"activity":"moderatelyActive","distance":1.33},{"activity":"lightlyActive","distance":2.81},{"activity":"sedentaryActive","distance":0}],"elevation":112.78,"fairlyActiveMinutes":26,"floors":37,"heartRateZones":[{"caloriesOut":1806.3648,"max":98,"min":30,"minutes":1217,"name":"Out of Range"},{"caloriesOut":744.17305,"max":137,"min":98,"minutes":107,"name":"Fat Burn"},{"caloriesOut":54.93895,"max":167,"min":137,"minutes":5,"name":"Cardio"},{"caloriesOut":0,"max":220,"min":167,"minutes":0,"name":"Peak"}],"lightlyActiveMinutes":173,"marginalCalories":858,"restingHeartRate":54,"sedentaryMinutes":579,"steps":10083,"veryActiveMinutes":46}}